stPackage_py
