Metadata-Version: 2.1
Name: stPackage-py
Version: 0.0.4
Summary: Este paqeute permite consumir el API de CódigoFacilito
Home-page: https://github.com/MarlettNuMa/FistPythonPackage
Author: Marlett Núñez
Author-email: marlett.numa@gmail.com
License: MIT
Keywords: curso codigofacilito
Platform: UNKNOWN
Classifier: Development Status :: 3 - Alpha
Classifier: Intended Audience :: Developers
Classifier: Topic :: Software Development :: Build Tools
Classifier: License :: OSI Approved :: MIT License
Classifier: Programming Language :: Python :: 3
License-File: LICENSE.txt
